[{"__type__":"cc.AnimationClip","_name":"rock_1","_duration":0.5166666666666667,"wrapMode":2,"curveData":{"comps":{"cc.Sprite":{"spriteFrame":[{"frame":0,"value":{"__uuid__":"f7SfgW0lVOPaayhRYOWN0k"}},{"frame":0.25,"value":{"__uuid__":"f49e+Bj19Ma4oi496gPd0T"}},{"frame":0.5,"value":{"__uuid__":"f7SfgW0lVOPaayhRYOWN0k"}}]}}}},{"__type__":"cc.AnimationClip","_name":"bat_2","_duration":0.5166666666666667,"wrapMode":2,"curveData":{"comps":{"cc.Sprite":{"spriteFrame":[{"frame":0,"value":{"__uuid__":"f212vxNFJCvaT/Ene5n8bC"}},{"frame":0.25,"value":{"__uuid__":"d98thO6+5J7rfgtV5tQinI"}},{"frame":0.5,"value":{"__uuid__":"f212vxNFJCvaT/Ene5n8bC"}}]}}}},{"__type__":"cc.SpriteFrame","content":{"name":"bat_2_2","texture":"c23pEZbl9JdoF8xlH4IFKo","rect":[0,34,30,31],"offset":[0,0],"originalSize":[30,31],"capInsets":[0,0,0,0]}},{"__type__":"cc.SpriteFrame","content":{"name":"bat_2_1","texture":"c23pEZbl9JdoF8xlH4IFKo","rect":[0,0,32,34],"offset":[0,0],"originalSize":[32,34],"capInsets":[0,0,0,0]}},{"__type__":"cc.SpriteFrame","content":{"name":"rock_1_2","texture":"57i5RRZ3pM17USbZuplz91","rect":[31,0,33,32],"offset":[0,0],"originalSize":[33,32],"capInsets":[0,0,0,0]}},{"__type__":"cc.SpriteFrame","content":{"name":"rock_1_1","texture":"57i5RRZ3pM17USbZuplz91","rect":[0,0,31,32],"offset":[0,0],"originalSize":[31,32],"capInsets":[0,0,0,0]}}]